cipher_util/__init__.py
cipher_util/caesar_cipher.py
cipher_util/cipher_api.py
cipher_util/cipher_tool.py
cipher_util-0.9.dist-info/METADATA
cipher_util-0.9.dist-info/WHEEL
cipher_util-0.9.dist-info/top_level.txt
cipher_util-0.9.dist-info/RECORD
