Metadata-Version: 2.1
Name: cipher_util
Version: 0.9
License: MIT
Classifier: Programming Language :: Python :: 3
Classifier: License :: OSI Approved :: MIT License
Classifier: Operating System :: OS Independent
Requires-Python: >=3.8.10
Requires-Dist: Flask >=2.0.0
Requires-Dist: setuptools
